{
  "aor": 0.0008822821576763486,
  "aqi": 0.023482987966804984,
  "bids_meta": {
    "dataset": "ds001233",
    "modality": "bold",
    "run_id": 3,
    "session_id": "pre",
    "subject_id": "05",
    "task_id": "cuedSFM"
  },
  "dummy_trs": 0,
  "dvars_nstd": 40.95285439491669,
  "dvars_std": 1.1789514723333339,
  "dvars_vstd": 0.9762460737083332,
  "efc": 0.5971722350638949,
  "fber": 1135.27734375,
  "fd_mean": 0.37662141068895444,
  "fd_num": 164,
  "fd_perc": 68.04979253112033,
  "fwhm_avg": 2.1151933333333335,
  "fwhm_x": 2.016185,
  "fwhm_y": 2.31852,
  "fwhm_z": 2.010875,
  "gcor": 0.00810401,
  "gsr_x": 0.00351099600084126,
  "gsr_y": 0.04759731888771057,
  "provenance": {
    "md5sum": "c57504a42eaeba2ff51fb14c0f69fad8",
    "settings": {
      "fd_thres": 0.2,
      "testing": false
    },
    "software": "mriqc",
    "version": "23.0.1",
    "webapi_port": null,
    "webapi_url": "https://mriqc.nimh.nih.gov/api/v1"
  },
  "size_t": 241,
  "size_x": 96,
  "size_y": 96,
  "size_z": 66,
  "snr": 5.526177176385793,
  "spacing_tr": 2.0,
  "spacing_x": 2.0,
  "spacing_y": 2.0,
  "spacing_z": 2.0,
  "summary_bg_k": 10.08303066449623,
  "summary_bg_mad": 14.538163695959057,
  "summary_bg_mean": 34.065208435058594,
  "summary_bg_median": 14.110343933105469,
  "summary_bg_n": 354604.0,
  "summary_bg_p05": 3.2609753608703613,
  "summary_bg_p95": 134.70421981811518,
  "summary_bg_stdv": 47.53805160522461,
  "summary_fg_k": 3.6169926591368533,
  "summary_fg_mad": 70.98220544583953,
  "summary_fg_mean": 489.3132019042969,
  "summary_fg_median": 486.0335693359375,
  "summary_fg_n": 162321.0,
  "summary_fg_p05": 355.01873779296875,
  "summary_fg_p95": 625.772705078125,
  "summary_fg_stdv": 87.95086669921875,
  "tsnr": 37.06209945678711
}